{"assets/.DS_Store":["assets/.DS_Store"],"assets/app-store.svg":["assets/app-store.svg"],"assets/email.png":["assets/email.png"],"assets/facebook.png":["assets/facebook.png"],"assets/getx.png":["assets/getx.png"],"assets/github.png":["assets/github.png"],"assets/gitlab.png":["assets/gitlab.png"],"assets/hive.png":["assets/hive.png"],"assets/hive.svg":["assets/hive.svg"],"assets/image_background.json":["assets/image_background.json"],"assets/image_background2.json":["assets/image_background2.json"],"assets/img.png":["assets/img.png"],"assets/instagram.png":["assets/instagram.png"],"assets/linkedin.png":["assets/linkedin.png"],"assets/my.png":["assets/my.png"],"assets/my2.png":["assets/my2.png"],"assets/my_logo.png":["assets/my_logo.png"],"assets/postman.svg":["assets/postman.svg"],"assets/provider.png":["assets/provider.png"],"assets/whatsapp.png":["assets/whatsapp.png"],"assets/x.png":["assets/x.png"],"assets/youtube.png":["assets/youtube.png"],"packages/cupertino_icons/assets/CupertinoIcons.ttf":["packages/cupertino_icons/assets/CupertinoIcons.ttf"],"packages/lecle_bubble_timeline/assets/screenshot.png":["packages/lecle_bubble_timeline/assets/screenshot.png"]}